README.rst
setup.py
airvacuumvald/__init__.py
airvacuumvald/airvacuum.py
airvacuumvald/tools.py
airvacuumvald.egg-info/PKG-INFO
airvacuumvald.egg-info/SOURCES.txt
airvacuumvald.egg-info/dependency_links.txt
airvacuumvald.egg-info/top_level.txt