Metadata-Version: 1.0
Name: airvacuumvald
Version: 23.7.17.0
Summary: Python implementation of the air-to-vacuum and vacuum-to-air wavelength conversion used by VALD (Vienna Atomic Line Database)
Home-page: https://github.com/trevisanj/airvacuumvald
Author: Julio Trevisan
Author-email: juliotrevisan@gmail.com
License: GNU GPLv3
Keywords: astronomy,astrophysics,vald,vald3,air,vacuum,wavelength,atomic lines
Platform: any
